README.md
setup.py
pyTamuGeocode/__init__.py
pyTamuGeocode.egg-info/PKG-INFO
pyTamuGeocode.egg-info/SOURCES.txt
pyTamuGeocode.egg-info/dependency_links.txt
pyTamuGeocode.egg-info/requires.txt
pyTamuGeocode.egg-info/top_level.txt