Metadata-Version: 1.0
Name: pyTamuGeocode
Version: 0.2
Summary: A library for working with Texas A&M's geocoding service
Home-page: https://github.com/jgillmanjr/pyTamuGeocode
Author: Jason Gillman Jr.
Author-email: mackdaddydiesel@gmail.com
License: UNKNOWN
Platform: UNKNOWN
